Sensor.vhd
library ieee;
use ieee.std_logic_1164.all;

entity Sensor is
port(
    sal_sensor : out std_logic
);
end entity;

architecture sens of Sensor is
    begin
    end architecture;

Electroiman.vhd
library ieee;
use ieee.std_logic_1164.all;

entity Electroiman is
port(
    act_electroiman : in std_logic;
    salida_electroiman : out std_logic
);
end entity;

architecture sens of Electroiman is
begin
    salida_electroiman <= act_electroiman;
end architecture;

Bomba.vhd
library ieee;
use ieee.std_logic_1164.all;

entity Bomba is
port(
    act_bomba : in std_logic
);
end entity;

architecture sens of Bomba is
begin
end architecture;

Motor.vhd
library ieee;
use ieee.std_logic_1164.all;

entity Motor is
port(
    med : in std_logic;
    alt : in std_logic
);
end entity;

architecture sens of Motor is
    begin

    end architecture;

Valvula.vhd
library ieee;
use ieee.std_logic_1164.all; 

entity Valvula is
    port(
        act_valvula : in std_logic
        );
end entity;

architecture sens of Valvula is
    begin

end architecture;

Lavarropas.vhd
library ieee;
use ieee.std_logic_1164.all;

-- /////////////////////////////////////////////
-- Declaración de los puertos de entrada y salida que se utilizaran.
entity Lavarropas is
port(
    perilla          : in std_logic_vector(2 downto 0) := "000";
    inicio           : in std_logic := '0';
    clk              : in std_logic := '0';
    led_tapa         : out std_logic := '0' ;
    led_lavado       : out std_logic := '0';
    led_centrifugado : out std_logic := '0';
    led_enjuague     : out std_logic := '0'
);
end entity;
-- /////////////////////////////////////////////

-- /////////////////////////////////////////////
-- Definición de la arquitectura asociada a las entidades.
-- A partir de aquí se describe la operación y organización del circuito.

architecture sens of Lavarropas is
    signal Contador : integer range 0 to 63 := 0;
    
----------- clases utilizadas
    component Motor
    port(
        med : in std_logic;
        alt : in std_logic
        );
    end component;
        
    component Bomba
    port(
        act_bomba : in std_logic
        );
    end component;

    component Valvula
    port(
        act_valvula : in std_logic
    );
    end component;

    component Sensor
    port(
        sal_sensor : out std_logic
    );
    end component;

    component Electroiman
    port(
        act_electroiman : in std_logic;
        salida_electroiman : out std_logic
    );
    end component;

---------- "cables" que indican las señales de cada entidad

    --CABLES 

    --Valvulas
    signal act_VJ : std_logic := '0';
    signal act_VS : std_logic := '0';
    signal act_VL : std_logic := '0';
    signal act_VV : std_logic := '0';

    --Motor
    signal alt : std_logic := '0';
    signal med : std_logic := '0';

    --Bomba
    signal act_bomba : std_logic := '0';

    --Electroiman
    signal act_electroiman : std_logic := '0';
    signal salida_electroiman : std_logic := '0';

    --Sensores
    signal sal_sensor0 : std_logic := '0';
    signal sal_sensor1 : std_logic := '0';
    signal sal_sensor2 : std_logic := '0';
    signal sal_sensor3 : std_logic := '0';
    signal sal_sensor4 : std_logic := '0';

    --Maquina de Estados
    signal state_reg  : std_logic_vector(4 downto 0);
    signal next_state : std_logic_vector(4 downto 0);

    --Bandera
    signal lavado_flag : std_logic_vector(1 downto 0) := "00";

    --Estados
    Constant IDLE         : std_logic_vector(4 downto 0) := "00001";
    Constant LAVADO       : std_logic_vector(4 downto 0) := "00010";
    Constant ENJUAGUE     : std_logic_vector(4 downto 0) := "00100";
    Constant CENTRIFUGADO : std_logic_vector(4 downto 0) := "01000";
    Constant DESAGOTE     : std_logic_vector(4 downto 0) := "10000";
    begin

    --Valvulas
    VS: Valvula port map(
        act_valvula => act_VS
    ); 
    VJ: Valvula port map(
        act_valvula => act_VJ
    );
    VL: Valvula port map(
        act_valvula => act_VL
    );
    VV: Valvula port map(
        act_valvula => act_VV
    );

    --Motor
    CVM: Motor port map(
        alt => alt,
        med => med
    );
    
    --Bomba
    CB: Bomba port map(
        act_bomba => act_bomba
    );

    --Electroiman
    TT: Electroiman port map(
        act_electroiman => act_electroiman,
        salida_electroiman => salida_electroiman
    );

    --Sensores
    S0: Sensor port map(
        sal_sensor => sal_sensor0
    );

    S1: Sensor port map(
        sal_sensor => sal_sensor1
    );

    S2: Sensor port map(
        sal_sensor => sal_sensor2
    );

    S3: Sensor port map(
        sal_sensor => sal_sensor3
    );

    S4: Sensor port map(
        sal_sensor => sal_sensor4
    );
--------SIGUIENTE ESTADO
    process(next_state)
    begin                            
        if next_state'event then
            state_reg <= next_state;
        end if;
    end process;

    process(clk)
    begin
        if rising_edge(clk) then
            Contador <= Contador + 1;
            led_tapa <= salida_electroiman;
            case state_reg is
--------IDLE Y ELECTROIMAN--------------------------------------------------------------------------------------------
                when IDLE=>
                    act_electroiman <= '0';
                    if inicio = '1' then
                        if perilla = "001" or perilla = "011" or perilla = "101" or perilla = "111" then
                            Contador <= 0;
                            next_state <= LAVADO;
                        end if;
                        if perilla = "110" or perilla = "010" then
                            Contador <= 0;
                            next_state <= ENJUAGUE;
                        end if;
                        if perilla = "100" then
                            Contador <= 0;
                            next_state <= CENTRIFUGADO;
                        end if;
                    else
                        Contador <= 0;
                        next_state <= IDLE;
                    end if;

--------LAVADO--------------------------------------------------------------------------------------------
                when LAVADO =>
                    
                    if Contador = 1 then 
                        act_electroiman <= '1';
                        led_lavado <= '1';
                        act_VJ <= '1';
                        act_VL <= '1';
                    elsif Contador = 6 then 
                        act_VJ <= '0';
                        act_VL <= '0';
                        if sal_sensor2 = '0' or sal_sensor4 = '1' then
                            Contador <= 0;
                            led_lavado <= '0';
                            lavado_flag <= "10";
                            next_state <= DESAGOTE;
                            else
                            med <= '1';
                        end if;
                    elsif Contador = 36 then
                            lavado_flag <= "01";
                            med <= '0';
                            Contador <= 0;
                            led_lavado <= '0';
                            next_state <= DESAGOTE;
                    end if;
                
--------ENJUAGUE--------------------------------------------------------------------------------------------
                when ENJUAGUE =>
                    if Contador = 1 then 
                        act_electroiman <= '1';
                        led_enjuague <= '1';
                        act_VS <= '1';
                        act_VL <= '1';
                    elsif Contador = 6 then 
                        act_VS <= '0';
                        act_VL <= '0';
                        if sal_sensor2 = '0' or sal_sensor4 = '1' then
                            Contador <= 0;
                            led_enjuague <= '0';
                            next_state <= DESAGOTE;
                            else
                            med <= '1';
                        end if;
                    elsif Contador = 36 then
                            med <= '0';
                            Contador <= 0;
                            led_enjuague <= '0';
                            next_state <= DESAGOTE;
                    end if;
                
--------CENTRIFUGADO--------------------------------------------------------------------------------------------
                when CENTRIFUGADO =>
                    if Contador = 1 then
                        led_centrifugado <= '1';
                        act_electroiman <= '1';
                        alt <= '1';
                    elsif Contador = 16 then
                        alt <= '0'; 
                        Contador <= 0;
                        led_centrifugado <= '0';
                        next_state <= IDLE;
                    end if;
--------DESAGOTE--------------------------------------------------------------------------------------------
                when DESAGOTE =>
                    if Contador = 1 then
                        act_VV <= '1';
                        act_bomba <= '1';
                    elsif Contador = 5 then
                        if perilla = "001" or perilla = "010" or lavado_flag = "10" then
                            Contador <= 0;
                            next_state <= IDLE;
                        elsif perilla = "101" or perilla = "110" then
                            Contador <= 0;
                            next_state <= CENTRIFUGADO;
                        elsif perilla = "111" or perilla = "011" then
                            if lavado_flag = "00" then
                                Contador <= 0;
                                next_state <= ENJUAGUE;
                            else 
                                lavado_flag <= "00";
                                if perilla = "111" then
                                    Contador <= 0;
                                    next_state <= CENTRIFUGADO;
                                else
                                    Contador <= 0;
                                    next_state <= IDLE;
                                end if;
                            end if;
                        end if;
                        act_bomba <= '0';
                        act_VV <= '0';
                    end if;
                when others =>
                Contador <= 0;
                next_state <= IDLE;
            end case;
        end if;   
    end process;

end architecture;
-- /////////////////////////////////////////////

Lavarropas_tb.vhd
library ieee;
use ieee.std_logic_1164.all;

entity Lavarropas_tb is
end entity;

architecture sens of Lavarropas_tb is
    component Lavarropas
    port(
        perilla          : in std_logic_vector(2 downto 0);
        inicio           : in std_logic;
        clk              : in std_logic;
        led_tapa         : out std_logic;
        led_lavado       : out std_logic;
        led_centrifugado : out std_logic;
        led_enjuague     : out std_logic
    );
    end component;

    
    signal perilla          :  std_logic_vector(2 downto 0) := (others =>  '0');
    signal inicio           :  std_logic;
    signal clk              :  std_logic := '0';
    signal led_tapa         :  std_logic;
    signal led_lavado       :  std_logic;
    signal led_centrifugado :  std_logic;
    signal led_enjuague     :  std_logic;


    constant clk_period : time := 1 ns;
begin
    uut: Lavarropas
    port map(
        perilla          => perilla,          
        inicio           => inicio,           
        clk              => clk,              
        led_tapa         => led_tapa,         
        led_lavado       => led_lavado,       
        led_centrifugado => led_centrifugado, 
        led_enjuague     => led_enjuague     
    );

    clk_process :process
        variable contadorTB : integer range 0 to 200 := 0;
        begin
        contadorTB := contadorTB + 1;
        if contadorTB < 199 then 
            clk <= '0';
            wait for clk_period/2;  --for 0.5 ns signal is '0'.
            clk <= '1';
            wait for clk_period/2;  --for next 0.5 ns signal is '1'.
        else
        wait;
        end if;
   end process;

   tb_process :process
        variable contador : integer := 0;
        begin
        inicio <= '1';
        perilla <= "000";
        perilla <= "111";
        wait for 0.5 ns;
        wait;
    end process;
        
end architecture;

lavarropas_tb.vcd
$date
  Sat Jun 25 11:24:00 2022
$end
$version
  GHDL v0
$end
$timescale
  1 fs
$end
$scope module standard $end
$upscope $end
$scope module std_logic_1164 $end
$upscope $end
$scope module lavarropas_tb $end
$var reg 3 ! perilla[2:0] $end
$var reg 1 " inicio $end
$var reg 1 # clk $end
$var reg 1 $ led_tapa $end
$var reg 1 % led_lavado $end
$var reg 1 & led_centrifugado $end
$var reg 1 ' led_enjuague $end
$scope module uut $end
$var reg 3 ( perilla[2:0] $end
$var reg 1 ) inicio $end
$var reg 1 * clk $end
$var reg 1 + led_tapa $end
$var reg 1 , led_lavado $end
$var reg 1 - led_centrifugado $end
$var reg 1 . led_enjuague $end
$var integer 32 / contador $end
$var reg 1 0 act_vj $end
$var reg 1 1 act_vs $end
$var reg 1 2 act_vl $end
$var reg 1 3 act_vv $end
$var reg 1 4 alt $end
$var reg 1 5 med $end
$var reg 1 6 act_bomba $end
$var reg 1 7 act_electroiman $end
$var reg 1 8 salida_electroiman $end
$var reg 1 9 sal_sensor0 $end
$var reg 1 : sal_sensor1 $end
$var reg 1 ; sal_sensor2 $end
$var reg 1 < sal_sensor3 $end
$var reg 1 = sal_sensor4 $end
$var reg 5 > state_reg[4:0] $end
$var reg 5 ? next_state[4:0] $end
$var reg 2 @ lavado_flag[1:0] $end
$scope module vs $end
$var reg 1 A act_valvula $end
$upscope $end
$scope module vj $end
$var reg 1 B act_valvula $end
$upscope $end
$scope module vl $end
$var reg 1 C act_valvula $end
$upscope $end
$scope module vv $end
$var reg 1 D act_valvula $end
$upscope $end
$scope module cvm $end
$var reg 1 E med $end
$var reg 1 F alt $end
$upscope $end
$scope module cb $end
$var reg 1 G act_bomba $end
$upscope $end
$scope module tt $end
$var reg 1 H act_electroiman $end
$var reg 1 I salida_electroiman $end
$upscope $end
$scope module s0 $end
$var reg 1 J sal_sensor $end
$upscope $end
$scope module s1 $end
$var reg 1 K sal_sensor $end
$upscope $end
$scope module s2 $end
$var reg 1 L sal_sensor $end
$upscope $end
$scope module s3 $end
$var reg 1 M sal_sensor $end
$upscope $end
$scope module s4 $end
$var reg 1 N sal_sensor $end
$upscope $end
$upscope $end
$upscope $end
$enddefinitions $end
#0
b111 !
1"
0#
0$
0%
0&
0'
b111 (
1)
0*
0+
0,
0-
0.
b0 /
00
01
02
03
04
05
06
07
08
U9
U:
U;
U<
U=
bUUUUU >
bUUUUU ?
b00 @
0A
0B
0C
0D
0E
0F
0G
0H
0I
UJ
UK
UL
UM
UN
#500000
1#
1*
b00001 >
b00001 ?
#1000000
0#
0*
#1500000
1#
1*
b00010 >
b00010 ?
#2000000
0#
0*
#2500000
1#
1*
b1 /
#3000000
0#
0*
#3500000
1#
1%
1*
1,
b10 /
10
12
17
18
1B
1C
1H
1I
#4000000
0#
0*
#4500000
1#
1$
1*
1+
b11 /
#5000000
0#
0*
#5500000
1#
1*
b100 /
#6000000
0#
0*
#6500000
1#
1*
b101 /
#7000000
0#
0*
#7500000
1#
1*
b110 /
#8000000
0#
0*
#8500000
1#
1*
b111 /
00
02
15
0B
0C
1E
#9000000
0#
0*
#9500000
1#
1*
b1000 /
#10000000
0#
0*
#10500000
1#
1*
b1001 /
#11000000
0#
0*
#11500000
1#
1*
b1010 /
#12000000
0#
0*
#12500000
1#
1*
b1011 /
#13000000
0#
0*
#13500000
1#
1*
b1100 /
#14000000
0#
0*
#14500000
1#
1*
b1101 /
#15000000
0#
0*
#15500000
1#
1*
b1110 /
#16000000
0#
0*
#16500000
1#
1*
b1111 /
#17000000
0#
0*
#17500000
1#
1*
b10000 /
#18000000
0#
0*
#18500000
1#
1*
b10001 /
#19000000
0#
0*
#19500000
1#
1*
b10010 /
#20000000
0#
0*
#20500000
1#
1*
b10011 /
#21000000
0#
0*
#21500000
1#
1*
b10100 /
#22000000
0#
0*
#22500000
1#
1*
b10101 /
#23000000
0#
0*
#23500000
1#
1*
b10110 /
#24000000
0#
0*
#24500000
1#
1*
b10111 /
#25000000
0#
0*
#25500000
1#
1*
b11000 /
#26000000
0#
0*
#26500000
1#
1*
b11001 /
#27000000
0#
0*
#27500000
1#
1*
b11010 /
#28000000
0#
0*
#28500000
1#
1*
b11011 /
#29000000
0#
0*
#29500000
1#
1*
b11100 /
#30000000
0#
0*
#30500000
1#
1*
b11101 /
#31000000
0#
0*
#31500000
1#
1*
b11110 /
#32000000
0#
0*
#32500000
1#
1*
b11111 /
#33000000
0#
0*
#33500000
1#
1*
b100000 /
#34000000
0#
0*
#34500000
1#
1*
b100001 /
#35000000
0#
0*
#35500000
1#
1*
b100010 /
#36000000
0#
0*
#36500000
1#
1*
b100011 /
#37000000
0#
0*
#37500000
1#
1*
b100100 /
#38000000
0#
0*
#38500000
1#
0%
1*
0,
b0 /
05
b10000 >
b10000 ?
b01 @
0E
#39000000
0#
0*
#39500000
1#
1*
b1 /
#40000000
0#
0*
#40500000
1#
1*
b10 /
13
16
1D
1G
#41000000
0#
0*
#41500000
1#
1*
b11 /
#42000000
0#
0*
#42500000
1#
1*
b100 /
#43000000
0#
0*
#43500000
1#
1*
b101 /
#44000000
0#
0*
#44500000
1#
1*
b0 /
03
06
b01000 >
b01000 ?
b00 @
0D
0G
#45000000
0#
0*
#45500000
1#
1*
b1 /
#46000000
0#
0*
#46500000
1#
1&
1*
1-
b10 /
14
1F
#47000000
0#
0*
#47500000
1#
1*
b11 /
#48000000
0#
0*
#48500000
1#
1*
b100 /
#49000000
0#
0*
#49500000
1#
1*
b101 /
#50000000
0#
0*
#50500000
1#
1*
b110 /
#51000000
0#
0*
#51500000
1#
1*
b111 /
#52000000
0#
0*
#52500000
1#
1*
b1000 /
#53000000
0#
0*
#53500000
1#
1*
b1001 /
#54000000
0#
0*
#54500000
1#
1*
b1010 /
#55000000
0#
0*
#55500000
1#
1*
b1011 /
#56000000
0#
0*
#56500000
1#
1*
b1100 /
#57000000
0#
0*
#57500000
1#
1*
b1101 /
#58000000
0#
0*
#58500000
1#
1*
b1110 /
#59000000
0#
0*
#59500000
1#
1*
b1111 /
#60000000
0#
0*
#60500000
1#
1*
b10000 /
#61000000
0#
0*
#61500000
1#
0&
1*
0-
b0 /
04
b00001 >
b00001 ?
0F
#62000000
0#
0*
#62500000
1#
1*
07
08
b00010 >
b00010 ?
0H
0I
#63000000
0#
0*
#63500000
1#
0$
1*
0+
b1 /
#64000000
0#
0*
#64500000
1#
1%
1*
1,
b10 /
10
12
17
18
1B
1C
1H
1I
#65000000
0#
0*
#65500000
1#
1$
1*
1+
b11 /
#66000000
0#
0*
#66500000
1#
1*
b100 /
#67000000
0#
0*
#67500000
1#
1*
b101 /
#68000000
0#
0*
#68500000
1#
1*
b110 /
#69000000
0#
0*
#69500000
1#
1*
b111 /
00
02
15
0B
0C
1E
#70000000
0#
0*
#70500000
1#
1*
b1000 /
#71000000
0#
0*
#71500000
1#
1*
b1001 /
#72000000
0#
0*
#72500000
1#
1*
b1010 /
#73000000
0#
0*
#73500000
1#
1*
b1011 /
#74000000
0#
0*
#74500000
1#
1*
b1100 /
#75000000
0#
0*
#75500000
1#
1*
b1101 /
#76000000
0#
0*
#76500000
1#
1*
b1110 /
#77000000
0#
0*
#77500000
1#
1*
b1111 /
#78000000
0#
0*
#78500000
1#
1*
b10000 /
#79000000
0#
0*
#79500000
1#
1*
b10001 /
#80000000
0#
0*
#80500000
1#
1*
b10010 /
#81000000
0#
0*
#81500000
1#
1*
b10011 /
#82000000
0#
0*
#82500000
1#
1*
b10100 /
#83000000
0#
0*
#83500000
1#
1*
b10101 /
#84000000
0#
0*
#84500000
1#
1*
b10110 /
#85000000
0#
0*
#85500000
1#
1*
b10111 /
#86000000
0#
0*
#86500000
1#
1*
b11000 /
#87000000
0#
0*
#87500000
1#
1*
b11001 /
#88000000
0#
0*
#88500000
1#
1*
b11010 /
#89000000
0#
0*
#89500000
1#
1*
b11011 /
#90000000
0#
0*
#90500000
1#
1*
b11100 /
#91000000
0#
0*
#91500000
1#
1*
b11101 /
#92000000
0#
0*
#92500000
1#
1*
b11110 /
#93000000
0#
0*
#93500000
1#
1*
b11111 /
#94000000
0#
0*
#94500000
1#
1*
b100000 /
#95000000
0#
0*
#95500000
1#
1*
b100001 /
#96000000
0#
0*
#96500000
1#
1*
b100010 /
#97000000
0#
0*
#97500000
1#
1*
b100011 /
#98000000
0#
0*
#98500000
1#
1*
b100100 /
#99000000
0#
0*
#99500000
1#
0%
1*
0,
b0 /
05
b10000 >
b10000 ?
b01 @
0E
#100000000
0#
0*
#100500000
1#
1*
b1 /
#101000000
0#
0*
#101500000
1#
1*
b10 /
13
16
1D
1G
#102000000
0#
0*
#102500000
1#
1*
b11 /
#103000000
0#
0*
#103500000
1#
1*
b100 /
#104000000
0#
0*
#104500000
1#
1*
b101 /
#105000000
0#
0*
#105500000
1#
1*
b0 /
03
06
b01000 >
b01000 ?
b00 @
0D
0G
#106000000
0#
0*
#106500000
1#
1*
b1 /
#107000000
0#
0*
#107500000
1#
1&
1*
1-
b10 /
14
1F
#108000000
0#
0*
#108500000
1#
1*
b11 /
#109000000
0#
0*
#109500000
1#
1*
b100 /
#110000000
0#
0*
#110500000
1#
1*
b101 /
#111000000
0#
0*
#111500000
1#
1*
b110 /
#112000000
0#
0*
#112500000
1#
1*
b111 /
#113000000
0#
0*
#113500000
1#
1*
b1000 /
#114000000
0#
0*
#114500000
1#
1*
b1001 /
#115000000
0#
0*
#115500000
1#
1*
b1010 /
#116000000
0#
0*
#116500000
1#
1*
b1011 /
#117000000
0#
0*
#117500000
1#
1*
b1100 /
#118000000
0#
0*
#118500000
1#
1*
b1101 /
#119000000
0#
0*
#119500000
1#
1*
b1110 /
#120000000
0#
0*
#120500000
1#
1*
b1111 /
#121000000
0#
0*
#121500000
1#
1*
b10000 /
#122000000
0#
0*
#122500000
1#
0&
1*
0-
b0 /
04
b00001 >
b00001 ?
0F
#123000000
0#
0*
#123500000
1#
1*
07
08
b00010 >
b00010 ?
0H
0I
#124000000
0#
0*
#124500000
1#
0$
1*
0+
b1 /
#125000000
0#
0*
#125500000
1#
1%
1*
1,
b10 /
10
12
17
18
1B
1C
1H
1I
#126000000
0#
0*
#126500000
1#
1$
1*
1+
b11 /
#127000000
0#
0*
#127500000
1#
1*
b100 /
#128000000
0#
0*
#128500000
1#
1*
b101 /
#129000000
0#
0*
#129500000
1#
1*
b110 /
#130000000
0#
0*
#130500000
1#
1*
b111 /
00
02
15
0B
0C
1E
#131000000
0#
0*
#131500000
1#
1*
b1000 /
#132000000
0#
0*
#132500000
1#
1*
b1001 /
#133000000
0#
0*
#133500000
1#
1*
b1010 /
#134000000
0#
0*
#134500000
1#
1*
b1011 /
#135000000
0#
0*
#135500000
1#
1*
b1100 /
#136000000
0#
0*
#136500000
1#
1*
b1101 /
#137000000
0#
0*
#137500000
1#
1*
b1110 /
#138000000
0#
0*
#138500000
1#
1*
b1111 /
#139000000
0#
0*
#139500000
1#
1*
b10000 /
#140000000
0#
0*
#140500000
1#
1*
b10001 /
#141000000
0#
0*
#141500000
1#
1*
b10010 /
#142000000
0#
0*
#142500000
1#
1*
b10011 /
#143000000
0#
0*
#143500000
1#
1*
b10100 /
#144000000
0#
0*
#144500000
1#
1*
b10101 /
#145000000
0#
0*
#145500000
1#
1*
b10110 /
#146000000
0#
0*
#146500000
1#
1*
b10111 /
#147000000
0#
0*
#147500000
1#
1*
b11000 /
#148000000
0#
0*
#148500000
1#
1*
b11001 /
#149000000
0#
0*
#149500000
1#
1*
b11010 /
#150000000
0#
0*
#150500000
1#
1*
b11011 /
#151000000
0#
0*
#151500000
1#
1*
b11100 /
#152000000
0#
0*
#152500000
1#
1*
b11101 /
#153000000
0#
0*
#153500000
1#
1*
b11110 /
#154000000
0#
0*
#154500000
1#
1*
b11111 /
#155000000
0#
0*
#155500000
1#
1*
b100000 /
#156000000
0#
0*
#156500000
1#
1*
b100001 /
#157000000
0#
0*
#157500000
1#
1*
b100010 /
#158000000
0#
0*
#158500000
1#
1*
b100011 /
#159000000
0#
0*
#159500000
1#
1*
b100100 /
#160000000
0#
0*
#160500000
1#
0%
1*
0,
b0 /
05
b10000 >
b10000 ?
b01 @
0E
#161000000
0#
0*
#161500000
1#
1*
b1 /
#162000000
0#
0*
#162500000
1#
1*
b10 /
13
16
1D
1G
#163000000
0#
0*
#163500000
1#
1*
b11 /
#164000000
0#
0*
#164500000
1#
1*
b100 /
#165000000
0#
0*
#165500000
1#
1*
b101 /
#166000000
0#
0*
#166500000
1#
1*
b0 /
03
06
b01000 >
b01000 ?
b00 @
0D
0G
#167000000
0#
0*
#167500000
1#
1*
b1 /
#168000000
0#
0*
#168500000
1#
1&
1*
1-
b10 /
14
1F
#169000000
0#
0*
#169500000
1#
1*
b11 /
#170000000
0#
0*
#170500000
1#
1*
b100 /
#171000000
0#
0*
#171500000
1#
1*
b101 /
#172000000
0#
0*
#172500000
1#
1*
b110 /
#173000000
0#
0*
#173500000
1#
1*
b111 /
#174000000
0#
0*
#174500000
1#
1*
b1000 /
#175000000
0#
0*
#175500000
1#
1*
b1001 /
#176000000
0#
0*
#176500000
1#
1*
b1010 /
#177000000
0#
0*
#177500000
1#
1*
b1011 /
#178000000
0#
0*
#178500000
1#
1*
b1100 /
#179000000
0#
0*
#179500000
1#
1*
b1101 /
#180000000
0#
0*
#180500000
1#
1*
b1110 /
#181000000
0#
0*
#181500000
1#
1*
b1111 /
#182000000
0#
0*
#182500000
1#
1*
b10000 /
#183000000
0#
0*
#183500000
1#
0&
1*
0-
b0 /
04
b00001 >
b00001 ?
0F
#184000000
0#
0*
#184500000
1#
1*
07
08
b00010 >
b00010 ?
0H
0I
#185000000
0#
0*
#185500000
1#
0$
1*
0+
b1 /
#186000000
0#
0*
#186500000
1#
1%
1*
1,
b10 /
10
12
17
18
1B
1C
1H
1I
#187000000
0#
0*
#187500000
1#
1$
1*
1+
b11 /
#188000000
0#
0*
#188500000
1#
1*
b100 /
#189000000
0#
0*
#189500000
1#
1*
b101 /
#190000000
0#
0*
#190500000
1#
1*
b110 /
#191000000
0#
0*
#191500000
1#
1*
b111 /
00
02
15
0B
0C
1E
#192000000
0#
0*
#192500000
1#
1*
b1000 /
#193000000
0#
0*
#193500000
1#
1*
b1001 /
#194000000
0#
0*
#194500000
1#
1*
b1010 /
#195000000
0#
0*
#195500000
1#
1*
b1011 /
#196000000
0#
0*
#196500000
1#
1*
b1100 /
#197000000
0#
0*
#197500000
1#
1*
b1101 /
