Lavarropas.vhd
library ieee;
use ieee.std_logic_1164.all;

entity Lavarropas is
port(
      -- Perilla
      perilla          : in std_logic_vector(2 downto 0) := "000";
      -- Boton inicio  
      inicio           : in std_logic  := '0';
      -- Clock                     
      clk              : in std_logic  := '0';
      -- Sensores                     
      sal_sensor0      : in std_logic  := '0';
      sal_sensor1      : in std_logic  := '0';                  
      sal_sensor2      : in std_logic  := '0';
      sal_sensor3      : in std_logic  := '0';
      sal_sensor4      : in std_logic  := '0';
      -- Valvulas  
      act_VL           : out std_logic  := '0';                    
      act_VS           : out std_logic  := '0';
      act_VJ           : out std_logic  := '0';
      act_VV           : out std_logic  := '0';
      -- Motor 
      med              : out std_logic  := '0';                    
      alt              : out std_logic  := '0';
      -- Bomba 
      act_bomba        : out std_logic  := '0';
      -- Electroiman                    
      act_electroiman  : out std_logic  := '0';
      -- Leds                    
      led_tapa         : out std_logic := '0';                   
      led_lavado       : out std_logic := '0';
      led_centrifugado : out std_logic := '0';
      led_enjuague     : out std_logic := '0'

);
end entity;
          
architecture sens of Lavarropas is
    --Contador
    signal cont : integer range 0 to 63 := 0;

    --Registro de estado
    signal state_reg  : std_logic_vector(5 downto 0);

    --Bandera
    signal camino : std_logic_vector(1 downto 0) := "00";

    --Estados
    Constant IDLE         : std_logic_vector(5 downto 0) := "000001";
    Constant LAVADO       : std_logic_vector(5 downto 0) := "000010";
    Constant ENJUAGUE     : std_logic_vector(5 downto 0) := "000100";
    Constant CENTRIFUGADO : std_logic_vector(5 downto 0) := "001000";
    Constant LLENADO      : std_logic_vector(5 downto 0) := "010000";
    Constant DESAGOTE     : std_logic_vector(5 downto 0) := "100000";
    
    begin
    process(clk)
    begin
        if rising_edge(clk) then
            cont <= cont + 1 ;
            case state_reg is
--------------------------------------------------- SELECTOR DEL PROGRAMA
                when IDLE=>
                    act_electroiman <= '0';
                    led_tapa <= '0';
                    if inicio = '1' then
                        if perilla = "001" or  perilla = "011" or  perilla = "101" or  perilla = "111" then
                            camino <= "00";
                            cont <= 0;
                            state_reg <= LLENADO;
                        elsif perilla = "010" or perilla = "110" then
                            camino <= "01";
                            cont <= 0;
                            state_reg <= LLENADO;
                        elsif perilla = "100" then
                            cont <= 0;
                            camino <= "11";
                            state_reg <= CENTRIFUGADO;
                        end if;
                    else
                        cont <= 0;
                        state_reg <= IDLE;
                    end if;
--------------------------------------------------- PROGRAMA LAVADO
                when LAVADO =>
                    act_electroiman <= '1';
                    led_tapa <= '1';
                    if cont = 1 then
                        led_lavado <= '1';
                        med <= '1';
                    elsif cont = 30 then --tiempo de lavado, 30 minutos
                        led_lavado <= '0';
                        med <= '0';
                        cont <= 0;
                        if perilla = "001" then
                            camino <= "11";
                        elsif perilla = "101" then
                            camino <= "10";
                        elsif perilla = "011" or perilla = "111" then
                            camino <= "01"; 
                        end if;
                        led_lavado <= '0';
                        cont <= 0;
                        state_reg <= DESAGOTE;
                    end if;
--------------------------------------------------- PROGRAMA ENJUAGUE
                when ENJUAGUE =>
                    act_electroiman <= '1';
                    led_tapa <= '1';
                    if cont = 1 then
                        led_enjuague <= '1';
                        med <= '1';
                    elsif cont = 30 then --tiempo de enjuague, 30 minutos
                        med <= '0';
                        cont <= 0;
                        led_enjuague <= '0';
                        if perilla = "010" or perilla = "011" then
                            camino <= "11";
                        elsif perilla = "110" or perilla = "111" then
                            camino <= "10";
                        end if;
                        led_enjuague <= '0';
                        state_reg <= DESAGOTE;
                    end if;
--------------------------------------------------- PROGRAMA CENTRIFUGADO
                when CENTRIFUGADO =>
                    act_electroiman <= '1';
                    led_tapa <= '1';
                    if cont = 1 then
                        led_centrifugado <= '1';
                        if sal_sensor0 = '1' then
                            led_centrifugado <= '0';
                            camino <= "10";
                            cont <= 0;
                            alt <= '0';
                            state_reg <= DESAGOTE;
                        else
                            alt <= '1';
                        end if;
                    elsif cont = 15 then --tiempo de centrifugado, 15 minutos
                        alt <= '0';
                        camino <= "00";
                        cont <= 0;
                        led_centrifugado <= '0';
                        state_reg <= DESAGOTE;
                    else 

                    end if;
--------------------------------------------------- PROGRAMA LLENADO
                when LLENADO =>
                    act_electroiman <= '1';
                    led_tapa <= '1';
                    if sal_sensor4 = '0' then
                        if cont = 1 and sal_sensor2 = '0' then
                            if camino = "00" then 
                                act_VL <= '1';
                                act_VJ <= '1';
                            elsif camino = "01" then
                                act_VL <= '1';
                                act_VS <= '1';
                            end if;
                        elsif sal_sensor2 = '1' and cont < 5 then --CASO DE ERROR CORTE DE AGUA
                            act_VL <= '0';
                            act_VS <= '0';
                            act_VJ <= '0';
                            if camino = "00" then
                                cont <= 0;
                                state_reg <= LAVADO;
                            else
                                cont <= 0;
                                state_reg <= ENJUAGUE;
                            end if;
                        elsif cont = 5 then
                            act_VL <= '0';
                            act_VS <= '0';
                            act_VJ <= '0'; 
                            camino <= "11";
                            cont <= 0;
                            state_reg <= DESAGOTE;
                        end if;
                    else --CASO DE ERROR SOBRELLENADO
                        act_VL <= '0';
                        act_VS <= '0';
                        act_VJ <= '0'; 
                        camino <= "11";
                        cont <= 0;
                        state_reg <= DESAGOTE;
                    end if;
--------------------------------------------------- PROGRAMA DESAGOTE
                when DESAGOTE =>
                    act_electroiman <= '1';
                    led_tapa <= '1';
                    if cont = 1 and sal_sensor0 = '1' then
                        act_bomba <= '1';
                        act_VV <= '1';
                    elsif cont > 1 and sal_sensor0 = '0' then
                        act_bomba <= '0';
                        act_VV <= '0';
                        if camino = "01" then
                            cont <= 0;
                            state_reg <= LLENADO;
                        elsif camino = "10" then
                            cont <= 0;
                            state_reg <= CENTRIFUGADO;
                        else
                            cont <= 0;
                            state_reg <= IDLE;
                        end if;
                    elsif cont = 5 and sal_sensor0 = '1' then --CASO DE ERROR NO ESTA VACIANDO (FLUJO OBSTRUIDO)
                        act_bomba <= '0';
                        cont <= 0;
                        state_reg <= IDLE;
                    elsif cont = 1 and sal_sensor0 = '0' then
                        act_bomba <= '0';
                        cont <= 0;
                        state_reg <= IDLE;
                    end if;
--------------------------------------------------- En caso de falla de memoria (estado inexistente)
                when others =>
                cont <= 0;
                state_reg <= IDLE;
            end case;
        end if;   
    end process;
end architecture;

Lavarropas_tb.vhd
library ieee;
use ieee.std_logic_1164.all;

entity Lavarropas_tb is
end entity;

architecture sens of Lavarropas_tb is
    component Lavarropas
    port(
      -- Perilla
      perilla          : in std_logic_vector(2 downto 0) := "000";
      -- Boton inicio  
      inicio           : in std_logic  := '0';
      -- Clock                     
      clk              : in std_logic  := '0';
      -- Sensores                     
      sal_sensor0      : in std_logic  := '0';
      sal_sensor1      : in std_logic  := '0';                  
      sal_sensor2      : in std_logic  := '0';
      sal_sensor3      : in std_logic  := '0';
      sal_sensor4      : in std_logic  := '0';
      -- Valvulas  
      act_VL           : out std_logic  := '0';                    
      act_VS           : out std_logic  := '0';
      act_VJ           : out std_logic  := '0';
      act_VV           : out std_logic  := '0';
      -- Motor 
      med              : out std_logic  := '0';                    
      alt              : out std_logic  := '0';
      -- Bomba 
      act_bomba        : out std_logic  := '0';
      -- Electroiman                    
      act_electroiman  : out std_logic  := '0';
      -- Leds                    
      led_tapa         : out std_logic := '0';                   
      led_lavado       : out std_logic := '0';
      led_centrifugado : out std_logic := '0';
      led_enjuague     : out std_logic := '0'

    );
    end component;

    -- Perilla
    signal perilla          :  std_logic_vector(2 downto 0) := (others =>  '0');
    -- Boton inicio  
    signal inicio           :  std_logic  := '0';
    -- Clock                     
    signal clk              : std_logic  := '0';
    -- Sensores                     
    signal sal_sensor0      : std_logic  := '0';
    signal sal_sensor1      : std_logic  := '0';                  
    signal sal_sensor2      : std_logic  := '0';
    signal sal_sensor3      : std_logic  := '0';
    signal sal_sensor4      : std_logic  := '0';
    -- Valvulas  
    signal act_VL           : std_logic  := '0';                    
    signal act_VS           : std_logic  := '0';
    signal act_VJ           : std_logic  := '0';
    signal act_VV           : std_logic  := '0';
    -- Motor 
    signal med              : std_logic  := '0';                    
    signal alt              : std_logic  := '0';
    -- Bomba 
    signal act_bomba        : std_logic  := '0';
    -- Electroiman                    
    signal act_electroiman  : std_logic  := '0';
    -- Leds                    
    signal led_tapa         : std_logic := '0';                   
    signal led_lavado       : std_logic := '0';
    signal led_centrifugado : std_logic := '0';
    signal led_enjuague     : std_logic := '0';
   

    constant clk_period : time := 1 ns;
begin
    uut: Lavarropas
    port map(
        -- Perilla
        perilla          => perilla,
        -- Boton inicio
        inicio           => inicio,
        -- Clock      
        clk              => clk,
        -- Sensores    
        sal_sensor0      => sal_sensor0,       
        sal_sensor1      => sal_sensor1,       
        sal_sensor2      => sal_sensor2,       
        sal_sensor3      => sal_sensor3,       
        sal_sensor4      => sal_sensor4,       
        -- Valvulas  
        act_VL           => act_VL,            
        act_VS           => act_VS,            
        act_VJ           => act_VJ,            
        act_VV           => act_VV,            
        -- Motor 
        med              => med,               
        alt              => alt,               
        -- Bomba 
        act_bomba        => act_bomba,         
        -- Electroiman  
        act_electroiman  => act_electroiman,   
        -- Leds         
        led_tapa         => led_tapa,          
        led_lavado       => led_lavado,        
        led_centrifugado => led_centrifugado,  
        led_enjuague     => led_enjuague      
);  

    clk_process :process
        variable contadorTB : integer range 0 to 10000 := 0;
        begin
        contadorTB := contadorTB + 1;
        if contadorTB < 9999 then 
            clk <= '0';
            wait for clk_period/2;  --for 0.5 ns signal is '0'.
            clk <= '1';
            wait for clk_period/2;  --for next 0.5 ns signal is '1'.
        else
        wait;
        end if;
   end process;

   tb_process :process
        variable contador : integer := 0;
        begin
            --perilla <= "000"; --IDLE
            --wait for 5 ns;
            --inicio <= '1';
            --wait for 3 ns;
            --inicio <= '0';
            --wait for 5 ns;
    
            perilla <= "111";
            inicio <= '1';
            wait for 5 ns;
            sal_sensor2 <= '1';
            sal_sensor0 <= '1';
            inicio <= '0';
            wait for 36 ns;
            sal_sensor2 <= '0';
            sal_sensor0 <= '0';
            wait for 6 ns;
            sal_sensor2 <= '1';
            sal_sensor0 <= '1';
            wait for 36 ns;
            sal_sensor2 <= '0';
            sal_sensor0 <= '0';
            wait for 10 ns;
            sal_sensor0 <= '1';
            wait for 11 ns;
            sal_sensor0 <= '0';

    
            --perilla <= "010"; --ENJUAGUE
            --inicio <= '1';
            --wait for 3 ns;
            --inicio <= '0';
            --wait for 50 ns;
    
            --perilla <= "100"; --CENTRIFUGADO
            --inicio <= '1';
            --wait for 3 ns;
            --inicio <= '0';
            --wait for 50 ns;
    --
            --perilla <= "011"; --LAVADO Y ENJUAGUE
            --inicio <= '1';
            --wait for 3 ns;
            --inicio <= '0';
            --wait for 100 ns;
    --
            --perilla <= "101"; --LAVADO Y CENTRIFUGADO
            --inicio <= '1';
            --wait for 3 ns;
            --inicio <= '0';
            --wait for 100 ns;
    --
            --perilla <= "110"; --ENJUAGUE Y CENTRIFUGADO
            --inicio <= '1';
            --wait for 3 ns;
            --inicio <= '0';
            --wait for 100 ns;
    --
            --perilla <= "111"; --LAVADO ENJUAGUE Y CENTRIFUGADO
            --inicio <= '1';
            --wait for 3 ns;
            --inicio <= '0';
            --wait for 100 ns;
        wait;
    end process;
        
end architecture;

lavarropas_tb.vcd
$date
  Sun Jul 10 18:38:17 2022
$end
$version
  GHDL v0
$end
$timescale
  1 fs
$end
$scope module standard $end
$upscope $end
$scope module std_logic_1164 $end
$upscope $end
$scope module lavarropas_tb $end
$var reg 3 ! perilla[2:0] $end
$var reg 1 " inicio $end
$var reg 1 # clk $end
$var reg 1 $ sal_sensor0 $end
$var reg 1 % sal_sensor1 $end
$var reg 1 & sal_sensor2 $end
$var reg 1 ' sal_sensor3 $end
$var reg 1 ( sal_sensor4 $end
$var reg 1 ) act_vl $end
$var reg 1 * act_vs $end
$var reg 1 + act_vj $end
$var reg 1 , act_vv $end
$var reg 1 - med $end
$var reg 1 . alt $end
$var reg 1 / act_bomba $end
$var reg 1 0 act_electroiman $end
$var reg 1 1 led_tapa $end
$var reg 1 2 led_lavado $end
$var reg 1 3 led_centrifugado $end
$var reg 1 4 led_enjuague $end
$scope module uut $end
$var reg 3 5 perilla[2:0] $end
$var reg 1 6 inicio $end
$var reg 1 7 clk $end
$var reg 1 8 sal_sensor0 $end
$var reg 1 9 sal_sensor1 $end
$var reg 1 : sal_sensor2 $end
$var reg 1 ; sal_sensor3 $end
$var reg 1 < sal_sensor4 $end
$var reg 1 = act_vl $end
$var reg 1 > act_vs $end
$var reg 1 ? act_vj $end
$var reg 1 @ act_vv $end
$var reg 1 A med $end
$var reg 1 B alt $end
$var reg 1 C act_bomba $end
$var reg 1 D act_electroiman $end
$var reg 1 E led_tapa $end
$var reg 1 F led_lavado $end
$var reg 1 G led_centrifugado $end
$var reg 1 H led_enjuague $end
$var integer 32 I cont $end
$var reg 6 J state_reg[5:0] $end
$var reg 2 K camino[1:0] $end
$upscope $end
$upscope $end
$enddefinitions $end
#0
b111 !
1"
0#
0$
0%
0&
0'
0(
0)
0*
0+
0,
0-
0.
0/
00
01
02
03
04
b111 5
16
07
08
09
0:
0;
0<
0=
0>
0?
0@
0A
0B
0C
0D
0E
0F
0G
0H
b0 I
bUUUUUU J
b00 K
#500000
1#
17
b000001 J
#1000000
0#
07
#1500000
1#
17
b010000 J
#2000000
0#
07
#2500000
1#
10
11
17
1D
1E
b1 I
#3000000
0#
07
#3500000
1#
1)
1+
17
1=
1?
b10 I
#4000000
0#
07
#4500000
1#
17
b11 I
#5000000
0"
0#
1$
1&
06
07
18
1:
#5500000
1#
0)
0+
17
0=
0?
b0 I
b000010 J
#6000000
0#
07
#6500000
1#
17
b1 I
#7000000
0#
07
#7500000
1#
1-
12
17
1A
1F
b10 I
#8000000
0#
07
#8500000
1#
17
b11 I
#9000000
0#
07
#9500000
1#
17
b100 I
#10000000
0#
07
#10500000
1#
17
b101 I
#11000000
0#
07
#11500000
1#
17
b110 I
#12000000
0#
07
#12500000
1#
17
b111 I
#13000000
0#
07
#13500000
1#
17
b1000 I
#14000000
0#
07
#14500000
1#
17
b1001 I
#15000000
0#
07
#15500000
1#
17
b1010 I
#16000000
0#
07
#16500000
1#
17
b1011 I
#17000000
0#
07
#17500000
1#
17
b1100 I
#18000000
0#
07
#18500000
1#
17
b1101 I
#19000000
0#
07
#19500000
1#
17
b1110 I
#20000000
0#
07
#20500000
1#
17
b1111 I
#21000000
0#
07
#21500000
1#
17
b10000 I
#22000000
0#
07
#22500000
1#
17
b10001 I
#23000000
0#
07
#23500000
1#
17
b10010 I
#24000000
0#
07
#24500000
1#
17
b10011 I
#25000000
0#
07
#25500000
1#
17
b10100 I
#26000000
0#
07
#26500000
1#
17
b10101 I
#27000000
0#
07
#27500000
1#
17
b10110 I
#28000000
0#
07
#28500000
1#
17
b10111 I
#29000000
0#
07
#29500000
1#
17
b11000 I
#30000000
0#
07
#30500000
1#
17
b11001 I
#31000000
0#
07
#31500000
1#
17
b11010 I
#32000000
0#
07
#32500000
1#
17
b11011 I
#33000000
0#
07
#33500000
1#
17
b11100 I
#34000000
0#
07
#34500000
1#
17
b11101 I
#35000000
0#
07
#35500000
1#
17
b11110 I
#36000000
0#
07
#36500000
1#
17
b11111 I
#37000000
0#
07
#37500000
1#
0-
02
17
0A
0F
b0 I
b100000 J
b01 K
#38000000
0#
07
#38500000
1#
17
b1 I
#39000000
0#
07
#39500000
1#
1,
1/
17
1@
1C
b10 I
#40000000
0#
07
#40500000
1#
17
b11 I
#41000000
0#
0$
0&
07
08
0:
#41500000
1#
0,
0/
17
0@
0C
b0 I
b010000 J
#42000000
0#
07
#42500000
1#
17
b1 I
#43000000
0#
07
#43500000
1#
1)
1*
17
1=
1>
b10 I
#44000000
0#
07
#44500000
1#
17
b11 I
#45000000
0#
07
#45500000
1#
17
b100 I
#46000000
0#
07
#46500000
1#
17
b101 I
#47000000
0#
1$
1&
07
18
1:
#47500000
1#
0)
0*
17
0=
0>
b0 I
b000100 J
#48000000
0#
07
#48500000
1#
17
b1 I
#49000000
0#
07
#49500000
1#
1-
14
17
1A
1H
b10 I
#50000000
0#
07
#50500000
1#
17
b11 I
#51000000
0#
07
#51500000
1#
17
b100 I
#52000000
0#
07
#52500000
1#
17
b101 I
#53000000
0#
07
#53500000
1#
17
b110 I
#54000000
0#
07
#54500000
1#
17
b111 I
#55000000
0#
07
#55500000
1#
17
b1000 I
#56000000
0#
07
#56500000
1#
17
b1001 I
#57000000
0#
07
#57500000
1#
17
b1010 I
#58000000
0#
07
#58500000
1#
17
b1011 I
#59000000
0#
07
#59500000
1#
17
b1100 I
#60000000
0#
07
#60500000
1#
17
b1101 I
#61000000
0#
07
#61500000
1#
17
b1110 I
#62000000
0#
07
#62500000
1#
17
b1111 I
#63000000
0#
07
#63500000
1#
17
b10000 I
#64000000
0#
07
#64500000
1#
17
b10001 I
#65000000
0#
07
#65500000
1#
17
b10010 I
#66000000
0#
07
#66500000
1#
17
b10011 I
#67000000
0#
07
#67500000
1#
17
b10100 I
#68000000
0#
07
#68500000
1#
17
b10101 I
#69000000
0#
07
#69500000
1#
17
b10110 I
#70000000
0#
07
#70500000
1#
17
b10111 I
#71000000
0#
07
#71500000
1#
17
b11000 I
#72000000
0#
07
#72500000
1#
17
b11001 I
#73000000
0#
07
#73500000
1#
17
b11010 I
#74000000
0#
07
#74500000
1#
17
b11011 I
#75000000
0#
07
#75500000
1#
17
b11100 I
#76000000
0#
07
#76500000
1#
17
b11101 I
#77000000
0#
07
#77500000
1#
17
b11110 I
#78000000
0#
07
#78500000
1#
17
b11111 I
#79000000
0#
07
#79500000
1#
0-
04
17
0A
0H
b0 I
b100000 J
b10 K
#80000000
0#
07
#80500000
1#
17
b1 I
#81000000
0#
07
#81500000
1#
1,
1/
17
1@
1C
b10 I
#82000000
0#
07
#82500000
1#
17
b11 I
#83000000
0#
0$
0&
07
08
0:
#83500000
1#
0,
0/
17
0@
0C
b0 I
b001000 J
#84000000
0#
07
#84500000
1#
17
b1 I
#85000000
0#
07
#85500000
1#
1.
13
17
1B
1G
b10 I
#86000000
0#
07
#86500000
1#
17
b11 I
#87000000
0#
07
#87500000
1#
17
b100 I
#88000000
0#
07
#88500000
1#
17
b101 I
#89000000
0#
07
#89500000
1#
17
b110 I
#90000000
0#
07
#90500000
1#
17
b111 I
#91000000
0#
07
#91500000
1#
17
b1000 I
#92000000
0#
07
#92500000
1#
17
b1001 I
#93000000
0#
1$
07
18
#93500000
1#
17
b1010 I
#94000000
0#
07
#94500000
1#
17
b1011 I
#95000000
0#
07
#95500000
1#
17
b1100 I
#96000000
0#
07
#96500000
1#
17
b1101 I
#97000000
0#
07
#97500000
1#
17
b1110 I
#98000000
0#
07
#98500000
1#
17
b1111 I
#99000000
0#
07
#99500000
1#
17
b10000 I
#100000000
0#
07
#100500000
1#
0.
03
17
0B
0G
b0 I
b100000 J
b00 K
#101000000
0#
07
#101500000
1#
17
b1 I
#102000000
0#
07
#102500000
1#
1,
1/
17
1@
1C
b10 I
#103000000
0#
07
#103500000
1#
17
b11 I
#104000000
0#
0$
07
08
#104500000
1#
0,
0/
17
0@
0C
b0 I
b000001 J
#105000000
0#
07
#105500000
1#
00
01
17
0D
0E
